examples_sir/__init__.py
examples_sir/stable_baselines3/__init__.py
examples_sir/stable_baselines3/mse.py
examples_sir/stable_baselines3/plot_png.py
examples_sir/stable_baselines3/reward_plot_2d_fc.py
examples_sir/stable_baselines3/reward_plot_2d_fs.py
examples_sir/stable_baselines3/sb3_sac_final.py
examples_sir/tuning/__init__.py
examples_sir/tuning/callbacks_sb3.py
examples_sir/tuning/tuning_sb3_sac.py
examples_sir/tuning/tuning_utils_sb3.py
gym_epidemic/__init__.py
gym_epidemic/envs/__init__.py
gym_epidemic/envs/sir_multi/InterventionSIR.py
gym_epidemic/envs/sir_multi/__init__.py
gym_epidemic/envs/sir_multi/env_sir_multi_morris.py
gym_epidemic/envs/sir_multi/optimize_interventions.py
gym_epidemic/envs/sir_multi/parameters.py
gym_epidemic/envs/sir_single/InterventionSIR.py
gym_epidemic/envs/sir_single/__init__.py
gym_epidemic/envs/sir_single/env_sir_morris.py
gym_epidemic/envs/sir_single/optimal_intervention.py
gym_epidemic/envs/sir_single/optimize_interventions.py
gym_epidemic/envs/sir_single/parameters.py
gym_epidemic-0.0.5.dist-info/LICENSE.txt
gym_epidemic-0.0.5.dist-info/METADATA
gym_epidemic-0.0.5.dist-info/WHEEL
gym_epidemic-0.0.5.dist-info/top_level.txt
gym_epidemic-0.0.5.dist-info/RECORD
